{
  "id": "ef0930a2-fa09-4934-b180-4e4177da65f9",
  "type": "MULTIPLE_CHOICE",
  "data": {
    "body": "Which of the following does NOT describe a necessary condition to pass parameters by address to a function",
    "solution": [
      0
    ],
    "answerChoices": [
      {
        "id": "1d49820c-c26b-4e6b-a3fc-ee6e7bedd30f",
        "index": 0,
        "body": "The number of function calls in a program can be reduced through the use of passing more parameters by address.",
        "questionId": "ef0930a2-fa09-4934-b180-4e4177da65f9",
        "stats": {
          "count": 4121
        },
        "resources": []
      },
      {
        "id": "fb28a5b0-d318-4c62-8766-bb09b2fac29d",
        "index": 1,
        "body": "More than a single value changed or calculated in the called function is needed in the calling function.",
        "questionId": "ef0930a2-fa09-4934-b180-4e4177da65f9",
        "stats": {
          "count": 1272
        },
        "resources": []
      },
      {
        "id": "239f769a-ad73-4acc-b7b9-bbe7acd47085",
        "index": 2,
        "body": "The called function completes only a single task of the larger problem being solved.",
        "questionId": "ef0930a2-fa09-4934-b180-4e4177da65f9",
        "stats": {
          "count": 1992
        },
        "resources": []
      },
      {
        "id": "1705de85-1d27-4762-b5f1-a4ea5ff82424",
        "index": 3,
        "body": "None of the above.",
        "questionId": "ef0930a2-fa09-4934-b180-4e4177da65f9",
        "stats": {
          "count": 715
        },
        "resources": []
      }
    ]
  },
  "number": 32,
  "disclaimer": "",
  "examId": "6a714cda-ab0f-4c46-ae64-b81861a5185a",
  "courseId": "803cbab7-3f7d-4912-9bf1-9812e893d445",
  "parentId": null,
  "flags": {
    "published": true,
    "disableRandomAnswers": false,
    "answersStartHidden": false
  },
  "stats": {
    "count": 1,
    "timeSpent": "816717662",
    "timeSpentVideo": "25473593",
    "submissions": 8325,
    "submissionsCorrect": 4121,
    "accuracy": 0.495015015015015,
    "difficulty": 0.7549258160237389
  },
  "resources": [],
  "exam": {
    "id": "6a714cda-ab0f-4c46-ae64-b81861a5185a",
    "number": 1,
    "year": 2021,
    "season": "FALL",
    "disclaimer": "",
    "courseId": "803cbab7-3f7d-4912-9bf1-9812e893d445",
    "flags": {
      "published": true,
      "practice": false
    },
    "stats": {
      "count": 1,
      "timeSpent": "28608093884",
      "timeSpentVideo": "785607084",
      "submissions": 235923,
      "submissionsCorrect": 152651,
      "questions": 34,
      "accuracy": 0.6470373808403589,
      "difficulty": 0.6030249170631675
    }
  },
  "explanation": {
    "id": "f661c83d-1eed-42f1-8c92-cdd3b174e1d8",
    "body": "",
    "questionId": "ef0930a2-fa09-4934-b180-4e4177da65f9",
    "resources": [
      {
        "id": "acc1fd39-0e36-4778-9d69-500fd142739e",
        "type": "VIDEO",
        "data": {
          "url": "https://youtu.be/R8kEmBxon5A?si=5BEzbKL0lgDM3OIj&t=2976"
        },
        "courseId": null,
        "examId": null,
        "questionId": null,
        "explanationId": "f661c83d-1eed-42f1-8c92-cdd3b174e1d8",
        "applicationId": null,
        "answerChoiceId": null,
        "customExamId": null
      }
    ]
  },
  "topics": [
    {
      "id": "9d34ecb4-85a1-4be8-a9b9-b63a0a9a3aae",
      "name": "True-False E1",
      "courseId": "803cbab7-3f7d-4912-9bf1-9812e893d445",
      "stats": {
        "count": 1,
        "timeSpent": "95415445580",
        "timeSpentVideo": "638704237",
        "submissions": 284157,
        "submissionsCorrect": 186372,
        "questions": 68,
        "accuracy": 0.6558768568080322,
        "difficulty": 0.5941779797858979
      }
    }
  ],
  "children": []
}