{
  "id": "568818c7-a20d-472d-a3e1-0069376f3155",
  "type": "MULTIPLE_CHOICE",
  "data": {
    "body": "Given $f(x)=14 x+2$, find and simplify the difference quotient\n\n\n\\[\n\\frac{f(x+h)-f(x)}{h}\n\\]",
    "solution": [
      4
    ],
    "answerChoices": [
      {
        "id": "3a072139-db08-4ad4-992a-debbfefa19b9",
        "index": 0,
        "body": "$4$",
        "questionId": "568818c7-a20d-472d-a3e1-0069376f3155",
        "stats": {
          "count": 51
        },
        "resources": []
      },
      {
        "id": "645bcd32-e941-4bef-a9ff-13a096315594",
        "index": 1,
        "body": "$\\frac{14}{h}$",
        "questionId": "568818c7-a20d-472d-a3e1-0069376f3155",
        "stats": {
          "count": 42
        },
        "resources": []
      },
      {
        "id": "f31c218c-aa26-4f6a-8599-017fa0fca8d5",
        "index": 2,
        "body": "$16$",
        "questionId": "568818c7-a20d-472d-a3e1-0069376f3155",
        "stats": {
          "count": 23
        },
        "resources": []
      },
      {
        "id": "9725d3f3-2e71-402a-9da6-9341275055ae",
        "index": 3,
        "body": "$14(x+h)+2$",
        "questionId": "568818c7-a20d-472d-a3e1-0069376f3155",
        "stats": {
          "count": 67
        },
        "resources": []
      },
      {
        "id": "00dad519-243c-4d66-939d-a6468c00c0db",
        "index": 4,
        "body": "$14$",
        "questionId": "568818c7-a20d-472d-a3e1-0069376f3155",
        "stats": {
          "count": 600
        },
        "resources": []
      },
      {
        "id": "7da48c28-aba0-446a-8a1c-8b502ae92d9e",
        "index": 5,
        "body": "$14\\left(\\frac{x}{h}\\right)+2$",
        "questionId": "568818c7-a20d-472d-a3e1-0069376f3155",
        "stats": {
          "count": 20
        },
        "resources": []
      }
    ]
  },
  "number": 10,
  "disclaimer": "",
  "examId": "126a578f-fc99-407b-9500-a9c789986e11",
  "courseId": "cb59f0bd-bbc3-4d92-bd9c-6bae411f3fc4",
  "parentId": null,
  "flags": {
    "published": true,
    "disableRandomAnswers": false,
    "answersStartHidden": false
  },
  "stats": {
    "count": 1,
    "timeSpent": "143159453",
    "timeSpentVideo": "14544652",
    "submissions": 1035,
    "submissionsCorrect": 600,
    "accuracy": 0.5797101449275363,
    "difficulty": 0.6773127753303965
  },
  "resources": [],
  "exam": {
    "id": "126a578f-fc99-407b-9500-a9c789986e11",
    "number": 1,
    "year": 2022,
    "season": "FALL",
    "disclaimer": "",
    "courseId": "cb59f0bd-bbc3-4d92-bd9c-6bae411f3fc4",
    "flags": {
      "published": true,
      "practice": false
    },
    "stats": {
      "count": 1,
      "timeSpent": "2342204807",
      "timeSpentVideo": "271512339",
      "submissions": 15537,
      "submissionsCorrect": 10046,
      "questions": 15,
      "accuracy": 0.6465855699298448,
      "difficulty": 0.6043518577732302
    }
  },
  "explanation": {
    "id": "e3e0d8b0-aba2-4f04-8fe3-4836e1d6cf5b",
    "body": "",
    "questionId": "568818c7-a20d-472d-a3e1-0069376f3155",
    "resources": [
      {
        "id": "a26fdd27-c2df-4c86-8678-777e0760c3f8",
        "type": "VIDEO",
        "data": {
          "url": "https://youtu.be/SDiQ2DqPZ10?si=2rU2zW3ar_dCTlGx&t=866\r"
        },
        "courseId": null,
        "examId": null,
        "questionId": null,
        "explanationId": "e3e0d8b0-aba2-4f04-8fe3-4836e1d6cf5b",
        "applicationId": null,
        "answerChoiceId": null,
        "customExamId": null
      }
    ]
  },
  "topics": [
    {
      "id": "e69ed633-0993-4035-86c5-2891af318d9c",
      "name": "The difference quotient",
      "courseId": "cb59f0bd-bbc3-4d92-bd9c-6bae411f3fc4",
      "stats": {
        "count": 1,
        "timeSpent": "1696995378",
        "timeSpentVideo": "14544652",
        "submissions": 2696,
        "submissionsCorrect": 1741,
        "questions": 3,
        "accuracy": 0.6457715133531158,
        "difficulty": 0.6094420600858369
      }
    }
  ],
  "children": []
}