{
  "id": "39a2adac-d002-4c33-944b-09a445d6cc14",
  "type": "MULTIPLE_CHOICE",
  "data": {
    "body": "The main function of the $\\rule{2.5cm}{0.4pt}$ is to absorb water and compact intestinal contents into feces.",
    "solution": [
      1
    ],
    "answerChoices": [
      {
        "id": "b120b2a4-2acb-465d-9c50-dd8973a8ec7a",
        "index": 0,
        "body": "Gallbladder",
        "questionId": "39a2adac-d002-4c33-944b-09a445d6cc14",
        "stats": {
          "count": 31
        },
        "resources": []
      },
      {
        "id": "a010596e-5b9a-4626-a72a-e3a7b619b985",
        "index": 1,
        "body": "Colon",
        "questionId": "39a2adac-d002-4c33-944b-09a445d6cc14",
        "stats": {
          "count": 559
        },
        "resources": []
      },
      {
        "id": "04117aaf-9677-4522-b8b4-c8de5e5a5f89",
        "index": 2,
        "body": "Pylorus",
        "questionId": "39a2adac-d002-4c33-944b-09a445d6cc14",
        "stats": {
          "count": 21
        },
        "resources": []
      },
      {
        "id": "c3a99a0f-ab11-4c45-a0d9-6d093caf9ed7",
        "index": 3,
        "body": "Antrum",
        "questionId": "39a2adac-d002-4c33-944b-09a445d6cc14",
        "stats": {
          "count": 12
        },
        "resources": []
      }
    ]
  },
  "number": 39,
  "disclaimer": "",
  "examId": "89c8d70c-ac45-462c-9427-e1a7e9b6d945",
  "courseId": "30949ec4-4915-44f1-ad9d-c08300116610",
  "parentId": null,
  "flags": {
    "published": true,
    "disableRandomAnswers": false,
    "answersStartHidden": false
  },
  "stats": {
    "count": 1,
    "timeSpent": "29208601",
    "timeSpentVideo": "0",
    "submissions": 650,
    "submissionsCorrect": 559,
    "accuracy": 0.86,
    "difficulty": 0.43799999999999994
  },
  "resources": [],
  "exam": {
    "id": "89c8d70c-ac45-462c-9427-e1a7e9b6d945",
    "number": 3,
    "year": 2023,
    "season": "SPRING",
    "disclaimer": "",
    "courseId": "30949ec4-4915-44f1-ad9d-c08300116610",
    "flags": {
      "published": true,
      "practice": false
    },
    "stats": {
      "count": 1,
      "timeSpent": "2600044402",
      "timeSpentVideo": "0",
      "submissions": 39460,
      "submissionsCorrect": 29934,
      "questions": 40,
      "accuracy": 0.758590978205778,
      "difficulty": 0.49206268958543986
    }
  },
  "explanation": {
    "id": "1903d877-7775-444e-a647-c60d3990f6d8",
    "body": "The colon's main function is to absorb water and to compact intestinal contents into feces. \n\nThe gallbladder stores and release bile produced by the liver. \n\nThe pylorus is a muscular region of the stomach near the small intestine. \n\nThe antrum is the lower portion of the stomach, between the body and the pylorus. ",
    "questionId": "39a2adac-d002-4c33-944b-09a445d6cc14",
    "resources": []
  },
  "topics": [
    {
      "id": "520ad936-1e0f-4d31-b6c4-26198d05b514",
      "name": "Digestive System",
      "courseId": "30949ec4-4915-44f1-ad9d-c08300116610",
      "stats": {
        "count": 1,
        "timeSpent": "1760325349",
        "timeSpentVideo": "0",
        "submissions": 8928,
        "submissionsCorrect": 7036,
        "questions": 15,
        "accuracy": 0.7880824372759857,
        "difficulty": 0.465108551174125
      }
    }
  ],
  "children": []
}