{
  "id": "3111d678-88ca-4625-b1ee-9dbe01976366",
  "type": "MULTIPLE_CHOICE",
  "data": {
    "body": "The anterior pituitary gland releases $\\rule{1.5cm}{0.4pt}$, which stimulates the secretion of testosterone by $\\rule{1.5cm}{0.4pt}$.",
    "solution": [
      3
    ],
    "answerChoices": [
      {
        "id": "a73146be-d2d5-4267-83a0-d12c314c5dac",
        "index": 0,
        "body": "FSH / Sperm cells",
        "questionId": "3111d678-88ca-4625-b1ee-9dbe01976366",
        "stats": {
          "count": 21
        },
        "resources": []
      },
      {
        "id": "bad9c2ec-c59d-4bf0-a49e-1ec5d908622d",
        "index": 1,
        "body": "FSH / Spermatogonia",
        "questionId": "3111d678-88ca-4625-b1ee-9dbe01976366",
        "stats": {
          "count": 47
        },
        "resources": []
      },
      {
        "id": "971a5a7a-04d5-4d04-8e33-e5ed952733bb",
        "index": 2,
        "body": "LH / Sertoli cells\n",
        "questionId": "3111d678-88ca-4625-b1ee-9dbe01976366",
        "stats": {
          "count": 101
        },
        "resources": []
      },
      {
        "id": "9c3e6646-57e2-4c29-9798-bb6a1b228cb3",
        "index": 3,
        "body": "LH / Leydig cells",
        "questionId": "3111d678-88ca-4625-b1ee-9dbe01976366",
        "stats": {
          "count": 610
        },
        "resources": []
      }
    ]
  },
  "number": 14,
  "disclaimer": "",
  "examId": "c0ad795e-9f4f-4823-8140-567e34dc192b",
  "courseId": "30949ec4-4915-44f1-ad9d-c08300116610",
  "parentId": null,
  "flags": {
    "published": true,
    "disableRandomAnswers": false,
    "answersStartHidden": false
  },
  "stats": {
    "count": 1,
    "timeSpent": "46926989",
    "timeSpentVideo": "0",
    "submissions": 794,
    "submissionsCorrect": 610,
    "accuracy": 0.7682619647355163,
    "difficulty": 0.511744966442953
  },
  "resources": [],
  "exam": {
    "id": "c0ad795e-9f4f-4823-8140-567e34dc192b",
    "number": 4,
    "year": 2023,
    "season": "SPRING",
    "disclaimer": "",
    "courseId": "30949ec4-4915-44f1-ad9d-c08300116610",
    "flags": {
      "published": true,
      "practice": false
    },
    "stats": {
      "count": 1,
      "timeSpent": "1933394278",
      "timeSpentVideo": "0",
      "submissions": 25276,
      "submissionsCorrect": 18912,
      "questions": 40,
      "accuracy": 0.7482196550087039,
      "difficulty": 0.5027585119798235
    }
  },
  "explanation": {
    "id": "187b2291-c909-4328-a238-f57cbcfda5fe",
    "body": "Luteinizing hormone (LH) is released by the anterior pituitary in response to gonadotropin-releasing hormone (GnRH).\n\n\\textit{\\textbf{L}}H then acts on \\textit{\\textbf{L}}eydig to release testosterone (remember L acts on L to secrete T). \n\nFollicle-stimulating hormone (F\\textit{\\textbf{S}}H) is also released by the anterior pituitary in response to GnRH, but acts on \\textit{\\textbf{S}}ertoli cells to stimulate \\textit{\\textbf{s}}perm production.  ",
    "questionId": "3111d678-88ca-4625-b1ee-9dbe01976366",
    "resources": []
  },
  "topics": [
    {
      "id": "d7794adb-777a-41a6-ae7c-e82c52cc336d",
      "name": "Male Reproductive System",
      "courseId": "30949ec4-4915-44f1-ad9d-c08300116610",
      "stats": {
        "count": 1,
        "timeSpent": "3389415836",
        "timeSpentVideo": "0",
        "submissions": 4707,
        "submissionsCorrect": 3692,
        "questions": 6,
        "accuracy": 0.7843637136180157,
        "difficulty": 0.47155190347410025
      }
    }
  ],
  "children": []
}