{
  "id": "8fb10661-6437-4448-845f-4e7076330747",
  "type": "MULTIPLE_CHOICE",
  "data": {
    "body": "What is the myenteric plexus?",
    "solution": [
      2
    ],
    "answerChoices": [
      {
        "id": "4dae774b-4c6b-4e3b-b0c0-011887f44558",
        "index": 0,
        "body": "The special smooth muscle surrounding the afferent arteriole at the glomerulus.",
        "questionId": "8fb10661-6437-4448-845f-4e7076330747",
        "stats": {
          "count": 47
        },
        "resources": []
      },
      {
        "id": "f0de2a1e-ac5a-4de6-a781-ef80ff6fcf80",
        "index": 1,
        "body": "A complex ecological system formed by all the microorganisms, including bacteria, fungi, and viruses, that live in our digestive tract.",
        "questionId": "8fb10661-6437-4448-845f-4e7076330747",
        "stats": {
          "count": 13
        },
        "resources": []
      },
      {
        "id": "ea4f154c-8faf-4ce2-b428-c59e2e1db530",
        "index": 2,
        "body": "A network of nerve fibers and ganglia between the longitudinal and circular muscle layers of the digestive organs that form part of the enteric nervous system.",
        "questionId": "8fb10661-6437-4448-845f-4e7076330747",
        "stats": {
          "count": 475
        },
        "resources": []
      },
      {
        "id": "bef382a2-0adc-4b39-88cb-783d4b8a0d60",
        "index": 3,
        "body": "A network of capillaries supplying blood to the organs of the digestive system.",
        "questionId": "8fb10661-6437-4448-845f-4e7076330747",
        "stats": {
          "count": 37
        },
        "resources": []
      }
    ]
  },
  "number": 28,
  "disclaimer": "",
  "examId": "89c8d70c-ac45-462c-9427-e1a7e9b6d945",
  "courseId": "30949ec4-4915-44f1-ad9d-c08300116610",
  "parentId": null,
  "flags": {
    "published": true,
    "disableRandomAnswers": false,
    "answersStartHidden": false
  },
  "stats": {
    "count": 1,
    "timeSpent": "35791212",
    "timeSpentVideo": "0",
    "submissions": 598,
    "submissionsCorrect": 475,
    "accuracy": 0.794314381270903,
    "difficulty": 0.49785100286532946
  },
  "resources": [],
  "exam": {
    "id": "89c8d70c-ac45-462c-9427-e1a7e9b6d945",
    "number": 3,
    "year": 2023,
    "season": "SPRING",
    "disclaimer": "",
    "courseId": "30949ec4-4915-44f1-ad9d-c08300116610",
    "flags": {
      "published": true,
      "practice": false
    },
    "stats": {
      "count": 1,
      "timeSpent": "2600044402",
      "timeSpentVideo": "0",
      "submissions": 39460,
      "submissionsCorrect": 29934,
      "questions": 40,
      "accuracy": 0.758590978205778,
      "difficulty": 0.49206268958543986
    }
  },
  "explanation": {
    "id": "621dd21d-c5bb-4fbf-8b99-860cd76ec4ca",
    "body": "The myenteric plexus is a network of nerve fibers and ganglia between the longitudinal and circular muscle layers of the digestive organs that form part of the enteric nervous system.\n\n Breaking the word down into it's component parts gives several clues as to what it is: \n\n$\\textbf{My/o-}$\nRefers to muscle tissue\n\n$\\textbf{Enter/o}$\nRefers to the intestine\n\n$\\textbf{-Ic}$\nPertaining to \n\n$\\textbf{Plexus}$\nA bundle of nerves\n\nSo, a network of nerves that are associated with muscle tissue in the intestine. \n\n",
    "questionId": "8fb10661-6437-4448-845f-4e7076330747",
    "resources": []
  },
  "topics": [
    {
      "id": "520ad936-1e0f-4d31-b6c4-26198d05b514",
      "name": "Digestive System",
      "courseId": "30949ec4-4915-44f1-ad9d-c08300116610",
      "stats": {
        "count": 1,
        "timeSpent": "1760325349",
        "timeSpentVideo": "0",
        "submissions": 8928,
        "submissionsCorrect": 7036,
        "questions": 15,
        "accuracy": 0.7880824372759857,
        "difficulty": 0.465108551174125
      }
    }
  ],
  "children": []
}