{
  "id": "995bd7f4-a266-48ca-910a-8b1123b49d11",
  "type": "MULTIPLE_CHOICE",
  "data": {
    "body": "Which of the following is the output generated by the program?",
    "solution": [
      1
    ],
    "answerChoices": [
      {
        "id": "fb369c77-e974-416e-bc1c-0a79456e26a4",
        "index": 0,
        "body": "Result: 3.8",
        "questionId": "995bd7f4-a266-48ca-910a-8b1123b49d11",
        "stats": {
          "count": 130
        },
        "resources": []
      },
      {
        "id": "8aac96be-6b7d-4551-9d96-e957d0d6422f",
        "index": 1,
        "body": "Result: 5.0",
        "questionId": "995bd7f4-a266-48ca-910a-8b1123b49d11",
        "stats": {
          "count": 2789
        },
        "resources": []
      },
      {
        "id": "2fd612af-c82a-4aa8-b540-7e1e0aa7bac3",
        "index": 2,
        "body": "Result: 5.8",
        "questionId": "995bd7f4-a266-48ca-910a-8b1123b49d11",
        "stats": {
          "count": 158
        },
        "resources": []
      },
      {
        "id": "77572772-7179-4b2c-84de-575de6256b8a",
        "index": 3,
        "body": "None of the above",
        "questionId": "995bd7f4-a266-48ca-910a-8b1123b49d11",
        "stats": {
          "count": 233
        },
        "resources": []
      }
    ]
  },
  "number": 3,
  "disclaimer": "",
  "examId": "1467f10c-a34d-4c9b-8223-bf3e59ada38f",
  "courseId": "803cbab7-3f7d-4912-9bf1-9812e893d445",
  "parentId": null,
  "flags": {
    "published": true,
    "disableRandomAnswers": false,
    "answersStartHidden": false
  },
  "stats": {
    "count": 1,
    "timeSpent": "318426070",
    "timeSpentVideo": "11562117",
    "submissions": 3355,
    "submissionsCorrect": 2789,
    "accuracy": 0.8312965722801788,
    "difficulty": 0.4282923299565846
  },
  "resources": [
    {
      "id": "d8649dc5-bc67-4717-acc4-0d52e55a4b50",
      "type": "CODE",
      "data": {
        "content": "#include <stdio.h>\n\ndouble makeCalc(int , int);\n\nint main()\n{\n  int x = 19;\n  int y = 4;\n\n  printf(\"Result: %.1lf\\n\", makeCalc(x,y));\n\n  return(0);\n}\n\ndouble makeCalc(int y, int z)\n{\n  return(y / z + 1);\n}",
        "language": "C"
      },
      "courseId": null,
      "examId": null,
      "questionId": "995bd7f4-a266-48ca-910a-8b1123b49d11",
      "explanationId": null,
      "applicationId": null,
      "answerChoiceId": null,
      "customExamId": null
    }
  ],
  "exam": {
    "id": "1467f10c-a34d-4c9b-8223-bf3e59ada38f",
    "number": 1,
    "year": 2020,
    "season": "FALL",
    "disclaimer": "",
    "courseId": "803cbab7-3f7d-4912-9bf1-9812e893d445",
    "flags": {
      "published": true,
      "practice": false
    },
    "stats": {
      "count": 1,
      "timeSpent": "11789365392",
      "timeSpentVideo": "678913940",
      "submissions": 113217,
      "submissionsCorrect": 77604,
      "questions": 25,
      "accuracy": 0.6854447653620923,
      "difficulty": 0.5647188859570939
    }
  },
  "explanation": {
    "id": "06663669-6012-4b80-900d-d1847a0fdf91",
    "body": "",
    "questionId": "995bd7f4-a266-48ca-910a-8b1123b49d11",
    "resources": [
      {
        "id": "4823cf9e-6e60-499b-9fcb-6f372886587d",
        "type": "VIDEO",
        "data": {
          "url": "https://youtu.be/glAA5XBQpgE?t=383"
        },
        "courseId": null,
        "examId": null,
        "questionId": null,
        "explanationId": "06663669-6012-4b80-900d-d1847a0fdf91",
        "applicationId": null,
        "answerChoiceId": null,
        "customExamId": null
      }
    ]
  },
  "topics": [
    {
      "id": "974dcc50-4f03-4a94-b09c-fba13dfc5a59",
      "name": "Functions",
      "courseId": "803cbab7-3f7d-4912-9bf1-9812e893d445",
      "stats": {
        "count": 1,
        "timeSpent": "30643002178",
        "timeSpentVideo": "459984181",
        "submissions": 103587,
        "submissionsCorrect": 70878,
        "questions": 41,
        "accuracy": 0.6842364389353877,
        "difficulty": 0.5659412462507354
      }
    }
  ],
  "children": []
}