{
  "id": "1935b9f9-ebb7-40b9-a875-75eea8431525",
  "type": "MULTIPLE_CHOICE",
  "data": {
    "body": "Find the RMS value of the following periodic voltage. ",
    "solution": [
      2
    ],
    "answerChoices": [
      {
        "id": "ed48f9a7-94c5-4d94-b209-536ed6a90333",
        "index": 0,
        "body": "7 V",
        "questionId": "1935b9f9-ebb7-40b9-a875-75eea8431525",
        "stats": {
          "count": 20
        },
        "resources": []
      },
      {
        "id": "26f217d6-304d-4ac7-8c50-0d6b896154f8",
        "index": 1,
        "body": "-4 V",
        "questionId": "1935b9f9-ebb7-40b9-a875-75eea8431525",
        "stats": {
          "count": 21
        },
        "resources": []
      },
      {
        "id": "afb189eb-3157-4472-8e2c-7a019c2a556e",
        "index": 2,
        "body": "2 V",
        "questionId": "1935b9f9-ebb7-40b9-a875-75eea8431525",
        "stats": {
          "count": 374
        },
        "resources": []
      },
      {
        "id": "3c7c90c6-f7db-46c6-ad50-536fd6b447c8",
        "index": 3,
        "body": "3 V",
        "questionId": "1935b9f9-ebb7-40b9-a875-75eea8431525",
        "stats": {
          "count": 34
        },
        "resources": []
      },
      {
        "id": "c250107c-0e4c-4e11-a320-d1eae6d71a79",
        "index": 4,
        "body": "-2 V",
        "questionId": "1935b9f9-ebb7-40b9-a875-75eea8431525",
        "stats": {
          "count": 2
        },
        "resources": []
      },
      {
        "id": "5a033317-7cab-46f3-9391-149117da1eb5",
        "index": 5,
        "body": "1.25 V",
        "questionId": "1935b9f9-ebb7-40b9-a875-75eea8431525",
        "stats": {
          "count": 23
        },
        "resources": []
      },
      {
        "id": "b05caf22-1b07-4dbf-8d83-c08332b30309",
        "index": 6,
        "body": "None of the above. ",
        "questionId": "1935b9f9-ebb7-40b9-a875-75eea8431525",
        "stats": {
          "count": 36
        },
        "resources": []
      }
    ]
  },
  "number": 6,
  "disclaimer": null,
  "examId": "16f38458-295f-40af-a46a-4f73e5fc69cd",
  "courseId": "eff5f02a-e609-42d1-a77f-8e9183c7e180",
  "parentId": null,
  "flags": {
    "published": true,
    "disableRandomAnswers": false,
    "answersStartHidden": false
  },
  "stats": {
    "count": 1,
    "timeSpent": "132620537",
    "timeSpentVideo": "29734324",
    "submissions": 704,
    "submissionsCorrect": 374,
    "accuracy": 0.53125,
    "difficulty": 0.722636815920398
  },
  "resources": [
    {
      "id": "0569dd46-8afb-4923-a0dc-eaf1becea0f6",
      "type": "IMAGE",
      "data": {
        "key": "_taACEWKQJzEUzVAI5BTJ",
        "url": "https://boilerexams-production.s3.us-east-2.amazonaws.com/_taACEWKQJzEUzVAI5BTJ"
      },
      "courseId": null,
      "examId": null,
      "questionId": "1935b9f9-ebb7-40b9-a875-75eea8431525",
      "explanationId": null,
      "applicationId": null,
      "answerChoiceId": null,
      "customExamId": null
    }
  ],
  "exam": {
    "id": "16f38458-295f-40af-a46a-4f73e5fc69cd",
    "number": 2,
    "year": 2023,
    "season": "SPRING",
    "disclaimer": "",
    "courseId": "eff5f02a-e609-42d1-a77f-8e9183c7e180",
    "flags": {
      "published": true,
      "practice": false
    },
    "stats": {
      "count": 1,
      "timeSpent": "1774352599",
      "timeSpentVideo": "471396110",
      "submissions": 8891,
      "submissionsCorrect": 5118,
      "questions": 12,
      "accuracy": 0.5756382859070971,
      "difficulty": 0.6752029807585364
    }
  },
  "explanation": {
    "id": "e0472d14-cf83-4e1a-aeb9-491cf729e7f1",
    "body": null,
    "questionId": "1935b9f9-ebb7-40b9-a875-75eea8431525",
    "resources": [
      {
        "id": "f73574c3-0319-4ab9-a1c3-72067556d4a1",
        "type": "VIDEO",
        "data": {
          "url": "https://youtu.be/OnYab_kSe2M?si=VzyQ6BRukGFq7pKy&t=1201"
        },
        "courseId": null,
        "examId": null,
        "questionId": null,
        "explanationId": "e0472d14-cf83-4e1a-aeb9-491cf729e7f1",
        "applicationId": null,
        "answerChoiceId": null,
        "customExamId": null
      }
    ]
  },
  "topics": [
    {
      "id": "3529ecce-d891-45fe-a00d-0054d9cf3bca",
      "name": "RMS Voltage & Current",
      "courseId": "eff5f02a-e609-42d1-a77f-8e9183c7e180",
      "stats": {
        "count": 1,
        "timeSpent": "554074441",
        "timeSpentVideo": "70890227",
        "submissions": 1660,
        "submissionsCorrect": 760,
        "questions": 2,
        "accuracy": 0.4578313253012048,
        "difficulty": 0.7897727272727273
      }
    }
  ],
  "children": []
}